log4py.py
log4py-2.1.dist-info/METADATA
log4py-2.1.dist-info/WHEEL
log4py-2.1.dist-info/top_level.txt
log4py-2.1.dist-info/zip-safe
log4py-2.1.dist-info/RECORD
